jwt/__init__.py
jwt/__main__.py
jwt/__version__.py
jwt/exceptions.py
jwt/http.py
jwt/jwt.py
jwt/jwt_api.py
jwt/util/__init__.py
jwt/util/exceptions.py
jwt/util/http.py
oktajwt/__init__.py
oktajwt/__main__.py
oktajwt/__version__.py
oktajwt/exceptions.py
oktajwt/http.py
oktajwt/jwt.py
oktajwt/jwt_api.py
oktajwt/main.py
oktajwt/util/__init__.py
oktajwt/util/exceptions.py
oktajwt/util/http.py
OktaJWT-1.0.0.dist-info/LICENSE
OktaJWT-1.0.0.dist-info/METADATA
OktaJWT-1.0.0.dist-info/WHEEL
OktaJWT-1.0.0.dist-info/entry_points.txt
OktaJWT-1.0.0.dist-info/top_level.txt
OktaJWT-1.0.0.dist-info/RECORD
