Metadata-Version: 2.1
Name: OktaJWT
Version: 1.0.0
Summary: A subset of RFC 7519 for working with JWTs minted by Okta API Access Management.
Home-page: https://github.com/mdwallick/okta-jwt
Author: Mike Wallick
Author-email: mike@wallick.net
License: GPLv3
Platform: UNKNOWN
Classifier: License :: OSI Approved :: GNU General Public License v3 (GPLv3)
Classifier: Development Status :: 4 - Beta
Classifier: Intended Audience :: Developers
Classifier: Natural Language :: English
Classifier: Programming Language :: Python
Classifier: Programming Language :: Python :: 3
Classifier: Programming Language :: Python :: 3.7
Requires-Python: >=3.7.0
Requires-Dist: cryptography
Requires-Dist: requests
